solutionfamily/engine.py
solutionfamily-1.0.9.dist-info/LICENSE
solutionfamily-1.0.9.dist-info/METADATA
solutionfamily-1.0.9.dist-info/WHEEL
solutionfamily-1.0.9.dist-info/top_level.txt
solutionfamily-1.0.9.dist-info/RECORD
