Metadata-Version: 2.1
Name: solutionfamily
Version: 1.0.9
Summary: A Python SDK for interacting with SolutionFamily's Solution Engine.
Home-page: https://github.com/SolutionFamily/engine-python-sdk
Maintainer: Chris Tacke
Maintainer-email: chris.tacke@solution-family.com
License: MIT
Download-URL: https://github.com/SolutionFamily/engine-python-sdk/dist/v1.0.0.tar.gz
Keywords: SolutionFamily,solutionengineiot,sdk
Platform: UNKNOWN
Classifier: License :: OSI Approved :: MIT License
Classifier: Programming Language :: Python :: 3
Requires-Dist: lxml
Requires-Dist: requests
Requires-Dist: python-dateutil
